{
  "TAO": {
    "ticker": "TAO",
    "coingecko_id": "bittensor",
    "price": 160.44,
    "price_change_24h": -3.0249246679663786,
    "market_cap": 1540015656.281136,
    "last_updated": "2026-02-09T13:29:51",
    "source": "coingecko",
    "timestamp": "2026-02-09T13:30:00.618409"
  },
  "SOL": {
    "ticker": "SOL",
    "coingecko_id": "solana",
    "price": 87.32,
    "price_change_24h": -0.07602871178515383,
    "market_cap": 49632340246.538376,
    "last_updated": "2026-02-09T13:29:51",
    "source": "coingecko",
    "timestamp": "2026-02-09T13:30:00.618418"
  },
  "ALL": {
    "ticker": "ALL",
    "coingecko_id": "fetch-ai",
    "price": 0.16139,
    "price_change_24h": -1.130185601955769,
    "market_cap": 368668380.2448905,
    "last_updated": "2026-02-09T13:29:52",
    "source": "coingecko",
    "timestamp": "2026-02-09T13:30:00.618423"
  },
  "PGR": {
    "ticker": "PGR",
    "coingecko_id": "upgrates",
    "price": 8.41e-06,
    "price_change_24h": null,
    "market_cap": 7584.199455941055,
    "last_updated": "2026-01-31T18:58:28",
    "source": "coingecko",
    "timestamp": "2026-02-09T13:30:00.618428"
  },
  "timestamp": "2026-02-09T13:30:00.618432"
}